pygenesis/__init__.py
pygenesis/main.py
pygenesis/package.py
pygenesis-1.1.0.dist-info/LICENSE
pygenesis-1.1.0.dist-info/METADATA
pygenesis-1.1.0.dist-info/WHEEL
pygenesis-1.1.0.dist-info/top_level.txt
pygenesis-1.1.0.dist-info/RECORD
