Metadata-Version: 2.1
Name: pygenesis
Version: 1.1.0
Summary: Python package repository template
Home-page: https://github.com/libresource/pygenesis
Author: quillcraftsman
Author-email: quill@craftsman.lol
License: MIT
Project-URL: Documentation, https://pygenesis.libresource.info
Project-URL: Source, https://github.com/libresource/pygenesis
Project-URL: Tracker, https://github.com/libresource/pygenesis/issues
Project-URL: Release notes, https://github.com/libresource/pygenesis/releases
Project-URL: Changelog, https://github.com/libresource/pygenesis/releases
Project-URL: Download, https://pypi.org/project/pygenesis/
Keywords: python,package,template-repository
Classifier: Development Status :: 5 - Production/Stable
Classifier: Intended Audience :: Developers
Classifier: License :: OSI Approved :: MIT License
Classifier: Programming Language :: Python :: 3
Classifier: Environment :: Console
Classifier: Operating System :: OS Independent
Classifier: Topic :: Software Development
Classifier: Topic :: Software Development :: Libraries
Classifier: Topic :: Software Development :: Libraries :: Python Modules
Requires-Python: >=3
License-File: LICENSE
